setup.py
jumpdir/__init__.py
jumpdir/bookmarks.py
jumpdir/directories.py
jumpdir/main.py
jumpdir/pathfinder.py
jumpdir.egg-info/PKG-INFO
jumpdir.egg-info/SOURCES.txt
jumpdir.egg-info/dependency_links.txt
jumpdir.egg-info/not-zip-safe
jumpdir.egg-info/requires.txt
jumpdir.egg-info/top_level.txt
scripts/jumpdir
scripts/jumpdir-search