Metadata-Version: 1.1
Name: jumpdir
Version: 0.7
Summary: A command line tool for quickly navigating your home directory.
Home-page: http://github.com/chrsintyre/jumpdir
Author: chrsintyre
Author-email: chrsintyre@gmail.com
License: MIT
Keywords: commandline navigation
Platform: UNKNOWN
Classifier: Development Status :: 3 - Alpha
Classifier: Intended Audience :: Developers
Classifier: Topic :: Utilities
Classifier: License :: OSI Approved :: MIT License
Classifier: Programming Language :: Python :: 2.7
Classifier: Programming Language :: Python :: 3
Classifier: Operating System :: POSIX :: Linux
